<annotation>
	<folder>images</folder>
	<filename>000153.jpg</filename>
	<path>/home/yeyupiaoling/data/plate_number/images/000153.jpg</path>
	<source>
		<database>Unknown</database>
	</source>
	<size>
		<width>400</width>
		<height>276</height>
		<depth>3</depth>
	</size>
	<segmented>0</segmented>
	<object>
		<name>plate_number</name>
		<pose>Unspecified</pose>
		<truncated>0</truncated>
		<difficult>0</difficult>
		<bndbox>
			<xmin>198</xmin>
			<ymin>160</ymin>
			<xmax>273</xmax>
			<ymax>185</ymax>
		</bndbox>
	</object>
	<object>
		<name>plate_number</name>
		<pose>Unspecified</pose>
		<truncated>0</truncated>
		<difficult>0</difficult>
		<bndbox>
			<xmin>51</xmin>
			<ymin>40</ymin>
			<xmax>72</xmax>
			<ymax>47</ymax>
		</bndbox>
	</object>
</annotation>
