<annotation>
	<folder>images</folder>
	<filename>000224.jpg</filename>
	<path>/home/yeyupiaoling/data/plate_number/images/000224.jpg</path>
	<source>
		<database>Unknown</database>
	</source>
	<size>
		<width>800</width>
		<height>600</height>
		<depth>3</depth>
	</size>
	<segmented>0</segmented>
	<object>
		<name>plate_number</name>
		<pose>Unspecified</pose>
		<truncated>0</truncated>
		<difficult>0</difficult>
		<bndbox>
			<xmin>271</xmin>
			<ymin>298</ymin>
			<xmax>479</xmax>
			<ymax>377</ymax>
		</bndbox>
	</object>
</annotation>
